MyOverlay/Overlay.py
MyOverlay/funcs/myfunctions.py
MyOverlay-0.5.5.dist-info/LICENSE
MyOverlay-0.5.5.dist-info/METADATA
MyOverlay-0.5.5.dist-info/WHEEL
MyOverlay-0.5.5.dist-info/top_level.txt
MyOverlay-0.5.5.dist-info/RECORD
