Metadata-Version: 2.1
Name: MyOverlay
Version: 0.5.5
Summary: Customized Text Only Screen Overlay
Author-email: Erik Reimann <erikreimann28@gmail.com>
Project-URL: Homepage, https://github.com/HerpesHabenderHauptmannHarry/MyOverlay
Project-URL: Bug Tracker, https://github.com/HerpesHabenderHauptmannHarry/MyOverlay/issues
Classifier: Programming Language :: Python :: 3
Classifier: License :: OSI Approved :: MIT License
Classifier: Operating System :: OS Independent
Requires-Python: >=3.7
License-File: LICENSE
Requires-Dist: pywin32 >=306
Requires-Dist: pywin32-ctypes >=0.2.2
Requires-Dist: pygame <=2.5.1
Requires-Dist: thefuzz >=0.19.0
